magic/__init__.py
magic/__main__.py
magic/add_spell.py
magic/cast_spell.py
magic/delete_spell.py
magic/edit_spellbook.py
magic/generate_commands.py
magic/get_help.py
magic/shared/__init__.py
magic/shared/config.py
magic/shared/display.py
magic/shared/prompt.py
magic/shared/spellbook.py
magic/shared/spellbook.schema.json
magic/shared/validation.py
magic/show_spell.py
tatuarvela_magic-3.1.3.dist-info/entry_points.txt
tatuarvela_magic-3.1.3.dist-info/LICENSE
tatuarvela_magic-3.1.3.dist-info/WHEEL
tatuarvela_magic-3.1.3.dist-info/METADATA
tatuarvela_magic-3.1.3.dist-info/RECORD
