Metadata-Version: 2.1
Name: tatuarvela-magic
Version: 3.1.3
Summary: A tool for simplifying repeated command line tasks
Home-page: https://github.com/TatuArvela/magic
License: MIT
Author: Tatu Arvela
Author-email: tatu.arvela@nitor.com
Requires-Python: >=3.7,<4.0
Classifier: License :: OSI Approved :: MIT License
Classifier: Programming Language :: Python :: 3
Classifier: Programming Language :: Python :: 3.10
Classifier: Programming Language :: Python :: 3.7
Classifier: Programming Language :: Python :: 3.8
Classifier: Programming Language :: Python :: 3.9
Requires-Dist: click (>=8.0.0,<9.0.0)
Requires-Dist: fastjsonschema (>=2.15.0,<3.0.0)
Requires-Dist: importlib-metadata (>=4.6.3,<5.0.0)
